{
  "indexes": [
    {
      "collectionGroup": "orders",
      "queryScope": "COLLECTION",
      "fields": [
        { "fieldPath": "userID", "order": "ASCENDING" },
        { "fieldPath": "date", "order": "DESCENDING" }
      ]
    },
    {
      "collectionGroup": "reservations",
      "queryScope": "COLLECTION",
      "fields": [
        { "fieldPath": "userID", "order": "ASCENDING" },
        { "fieldPath": "createdAt", "order": "DESCENDING" }
      ]
    },
    {
      "collectionGroup": "reservations",
      "queryScope": "COLLECTION",
      "fields": [
        { "fieldPath": "date", "order": "ASCENDING" },
        { "fieldPath": "time", "order": "ASCENDING" },
        { "fieldPath": "tableNumber", "order": "ASCENDING" },
        { "fieldPath": "status", "order": "ASCENDING" }
      ]
    },
    {
      "collectionGroup": "leaderboard",
      "queryScope": "COLLECTION",
      "fields": [
        { "fieldPath": "points", "order": "DESCENDING" }
      ]
    },
    {
      "collectionGroup": "drinks",
      "queryScope": "COLLECTION",
      "fields": [
        { "fieldPath": "moodTag", "order": "ASCENDING" },
        { "fieldPath": "available", "order": "ASCENDING" }
      ]
    }
  ],
  "fieldOverrides": []
}
